sqsall/__init__.py
awscli_sqsall-1.0.2.dist-info/LICENSE
awscli_sqsall-1.0.2.dist-info/METADATA
awscli_sqsall-1.0.2.dist-info/WHEEL
awscli_sqsall-1.0.2.dist-info/top_level.txt
awscli_sqsall-1.0.2.dist-info/RECORD
