Metadata-Version: 2.1
Name: awscli-sqsall
Version: 1.0.2
Summary: awscli plugin to treat SQS queues more like files
Home-page: https://github.com/pkoch/awscli-sqsall
Author: Paulo Köch
Author-email: paulo.koch@gmail.com
License: MIT
Project-URL: Bug Tracker, https://github.com/pkoch/awscli-sqsall/issues
Platform: UNKNOWN
Classifier: Development Status :: 3 - Alpha
Classifier: Intended Audience :: Developers
Classifier: Intended Audience :: System Administrators
Classifier: Natural Language :: English
Classifier: Programming Language :: Python
Classifier: Programming Language :: Python :: 3
Classifier: Programming Language :: Python :: 3.6
Classifier: Programming Language :: Python :: 3.7
Classifier: Programming Language :: Python :: 3.8
Classifier: Programming Language :: Python :: 3.9
Requires-Python: >=3.6
License-File: LICENSE
Requires-Dist: awscli (>=1.16.140)
